{
  "network/mobile/general": {
    "description": "mobile general configuration",
    "write": {
      "api": ["/modems/*", "/sim_cards/*", "/operator_lists/*"],
      "uci": ["simcard", "overview", "operctl"]
    },
    "read": {
      "api": ["/modems/*", "/sim_cards/*", "/operator_lists/*"],
      "uci": ["simcard", "operctl", "overview"],
      "ubus": {
        "gsmd": ["reinit_modems"]
      }
    }
  },

  "network/mobile/sim_switch": {
    "description": "mobile sim switch configuration",
    "read": {
      "api": ["/modems/*", "/sim_cards/*", "/sim_switch/*"],
      "uci": ["sim_switch", "simcard"],
      "ubus": {
        "vuci.network.mobile": ["get_all_modems"],
        "sim": ["get"]
      }
    },
    "write": {
      "api": ["/modems/*", "/sim_cards/*", "/sim_switch/*"],
      "uci": ["sim_switch", "simcard"]
    }
  },

  "network/mobile/operators/scan": {
    "description": "mobile operators configuration",
    "read": {
      "api": ["/modems/*", "/sim_cards/*"],
      "uci": ["simcard"],
      "ubus": {
        "vuci.network.mobile": ["get_all_modems"],
        "sim": ["get"]
      }
    },
    "write": {
      "api": ["/modems/*", "/sim_cards/*"],
      "uci": ["simcard"],
      "ubus": {
        "gsmd": ["reinit_modems"]
      }
    }
  },

  "network/mobile/operators/list": {
    "description": "mobile operators configuration",
    "write": {
      "api": ["/modems/*", "/operator_lists/*"],
      "uci": ["operctl", "simcard"],
      "ubus": {
        "gsmd": ["reinit_modems"]
      }
    },
    "read": {
      "api": ["/modems/*", "/operator_lists/*"],
      "uci": ["operctl", "simcard"]
    }
  },

  "network/mobile/apn_database": {
    "read": {
      "api": ["/apn_database/*"]
    },
    "write": {
      "api": ["/apn_database/*"]
    }
  },

  "network/mobile/esim_profiles": {
    "read": {
      "api": ["/modems/*", "/esim/*"]
    },
    "write": {
      "api": ["/modems/*", "/esim/*"]
    }
  }
}
