{
  "openapi": "3.0.0",
  "paths": {
    "/tinc/{id}/hosts/config": {
      "get": {
        "summary": "Returns all Tinc VPN Host configurations",
        "responses": {
          "200": {
            "$ref": "#/components/responses/200TincHostMulti"
          },
          "404": {
            "$ref": "#/components/responses/404response"
          }
        },
        "tags": ["Host"]
      },
      "post": {
        "summary": "Creates Tinc VPN Host configuration",
        "responses": {
          "201": {
            "$ref": "#/components/responses/200TincHost"
          },
          "422": {
            "$ref": "#/components/responses/422response"
          }
        },
        "requestBody": {
          "description": "Parameter section",
          "content": {
            "application/json": {
              "schema": {
                "type": "object",
                "properties": {
                  "data": {
                    "$ref": "#/components/schemas/tinc_host_options"
                  }
                }
              }
            }
          }
        },
        "tags": ["Host"]
      },
      "put": {
        "summary": "Updates specified Tinc VPN Hosts configurations",
        "responses": {
          "200": {
            "$ref": "#/components/responses/200TincHostMulti"
          },
          "404": {
            "$ref": "#/components/responses/404response"
          },
          "422": {
            "$ref": "#/components/responses/422response"
          }
        },
        "requestBody": {
          "description": "Parameter section",
          "content": {
            "application/json": {
              "schema": {
                "type": "object",
                "properties": {
                  "data": {
                    "type": "array",
                    "description": "Array of section objects",
                    "items": {
                      "$ref": "#/components/schemas/tinc_host_options"
                    }
                  }
                }
              }
            }
          }
        },
        "tags": ["Host"],
        "operationId": ""
      },
      "delete": {
        "summary": "Deletes specified Tinc VPN Host configurations",
        "responses": {
          "200": {
            "$ref": "#/components/responses/200deleted_multi"
          },
          "404": {
            "$ref": "#/components/responses/404response"
          }
        },
        "requestBody": {
          "description": "Parameter section",
          "content": {
            "application/json": {
              "schema": {
                "type": "object",
                "properties": {
                  "data": {
                    "type": "array",
                    "description": "Array of section objects",
                    "items": {
                      "type": "string",
                      "description": "Configuration id"
                    }
                  }
                }
              }
            }
          }
        },
        "tags": ["Host"],
        "description": "",
        "operationId": ""
      },
      "parameters": [
        {
          "schema": {
            "type": "string"
          },
          "name": "id",
          "in": "path",
          "required": true,
          "description": "Tinc Configuration identifier (ID)"
        }
      ],
      "x-web": {
        "menu": ["Services", "VPN", "Tinc"],
        "hw_tags": {
          "is_switch": false,
          "is_access_point": false
        }
      }
    },
    "/tinc/{id}/hosts/config/{hosts_id}": {
      "get": {
        "summary": "Returns the specified Tinc VPN Host configuration",
        "responses": {
          "200": {
            "$ref": "#/components/responses/200TincHost"
          },
          "404": {
            "$ref": "#/components/responses/404response"
          }
        },
        "tags": ["Host"]
      },
      "put": {
        "summary": "Updates the specified Tinc VPN Host configuration",
        "responses": {
          "200": {
            "$ref": "#/components/responses/200TincHost"
          },
          "404": {
            "$ref": "#/components/responses/404response"
          },
          "422": {
            "$ref": "#/components/responses/422response"
          }
        },
        "requestBody": {
          "description": "Parameter section",
          "content": {
            "application/json": {
              "schema": {
                "type": "object",
                "properties": {
                  "data": {
                    "$ref": "#/components/schemas/tinc_host_single_options"
                  }
                }
              }
            }
          }
        },
        "tags": ["Host"],
        "description": ""
      },
      "delete": {
        "summary": "Deletes the specified Tinc VPN Host configuration",
        "responses": {
          "200": {
            "$ref": "#/components/responses/200deleted"
          },
          "404": {
            "$ref": "#/components/responses/404response"
          }
        },
        "tags": ["Host"]
      },
      "parameters": [
        {
          "schema": {
            "type": "string"
          },
          "name": "id",
          "in": "path",
          "required": true,
          "description": "Tinc Configuration identifier (ID)"
        },
        {
          "schema": {
            "type": "string"
          },
          "name": "hosts_id",
          "in": "path",
          "required": true,
          "description": "Tinc Host Configuration identifier (ID)"
        }
      ],
      "x-web": {
        "menu": ["Services", "VPN", "Tinc"],
        "hw_tags": {
          "is_switch": false,
          "is_access_point": false
        }
      }
    }
  },
  "components": {
    "responses": {
      "200TincHost": {
        "description": "Returns configuration",
        "content": {
          "application/json": {
            "schema": {
              "type": "object",
              "properties": {
                "success": {
                  "type": "boolean",
                  "description": "Operation status"
                },
                "data": {
                  "$ref": "#/components/schemas/tinc_host_option_net"
                }
              }
            }
          }
        }
      },
      "200TincHostMulti": {
        "description": "Returns configurations",
        "content": {
          "application/json": {
            "schema": {
              "type": "object",
              "properties": {
                "success": {
                  "type": "boolean",
                  "description": "Operation status"
                },
                "data": {
                  "type": "array",
                  "description": "Array of section objects",
                  "items": {
                    "$ref": "#/components/schemas/tinc_host_option_net"
                  }
                }
              }
            }
          }
        }
      }
    },
    "schemas": {
      "tinc_host_options": {
        "allOf": [
          {
            "type": "object",
            "properties": {
              "id": {
                "x-web": {
                  "pretty": "Tinc host configuration name",
                  "unique": true,
                  "input-type": "input"
                },
                "type": "string",
                "description": "Tinc Host Configuration identifier (ID)."
              }
            },
            "required": ["id"]
          },
          {
            "$ref": "#/components/schemas/tinc_host_single_options"
          }
        ]
      },
      "tinc_host_single_options": {
        "type": "object",
        "properties": {
          "enabled": {
            "x-web": {
              "pretty": "Enabled",
              "input-type": "switch"
            },
            "type": "string",
            "description": "Enables/disables Tinc Host instance.",
            "format": "is_bool",
            "enum": ["0", "1"]
          },
          "address": {
            "x-web": {
              "pretty": "Address",
              "input-type": "input"
            },
            "type": "array",
            "description": "It must resolve to the external IP address where the host can be reached, not the one that is internal to the VPN.",
            "format": "host",
            "items": {
              "type": "string"
            }
          },
          "subnet": {
            "x-web": {
              "pretty": "Subnet",
              "input-type": "input"
            },
            "type": "array",
            "description": "The subnet which this tinc daemon will serve. Multiple subnet lines can be specified for each Daemon.",
            "format": "ipmask",
            "items": {
              "type": "string"
            }
          },
          "publickeyfile": {
            "x-web": {
              "pretty": "Public Key",
              "input-type": "input"
            },
            "type": "string",
            "format": "binary",
            "description": "RSA public key generated by host."
          },
          "description": {
            "type": "string",
            "description": "Description of host."
          }
        }
      },
      "tinc_host_option_net": {
        "title": "tinc_host_option_net",
        "x-stoplight": {
          "id": "zfvx1bnr5dhd7"
        },
        "allOf": [
          {
            "type": "object",
            "properties": {
              "id": {
                "type": "string",
                "description": "Tinc Host Configuration identifier (ID)."
              },
              "net": {
                "type": "string",
                "description": "Instance name to which the host belongs."
              }
            }
          },
          {
            "$ref": "#/components/schemas/tinc_host_single_options"
          }
        ]
      }
    }
  },
  "info": {
    "version": "1.0",
    "title": "Tinc host",
    "description": "Tinc host api documentation"
  },
  "tags": [
    {
      "name": "Host"
    }
  ]
}
