{"services/io/juggler/input":{"description":"input.output juggler configuration","read":{"api":{"/io/status/*":["*"],"/io/juggler/inputs/config/*":["*"],"/io/juggler/global/*":["*"],"/io/juggler/conditions/config/*":["ui_name"],"/io/juggler/operations/config/*":["*"],"/io/scheduler/config/*":["*"],"/io/scheduler/global/*":["*"]}},"write":{"api":["/io/juggler/inputs/config/*","/io/juggler/global/*"]}},"services/io/juggler/action":{"description":"input.output juggler actions configuration","read":{"api":{"/io/status/*":["*"],"/io/juggler/operations/options/*":["*"],"/io/juggler/operations/config/*":["*"],"/io/juggler/conditions/config/*":["ui_name"],"/recipients/email_users/config/*":["name"],"/recipients/phone_groups/config/*":["name"],"/sim_switch/config/*":["position"],"/modems/status/*":["id","name","index","builtin","operator_state","operator","provider","cell_info"],"/profiles/config/*":["id"],"/basic/network/devices/status/*":["*"],"/certificates/config/*":["fullname","type","cert_type"]}},"write":{"api":["/io/juggler/operations/config/*"]},"source":["/io/juggler/operations/*"],"exception":["/io/juggler/operations/config/*"]},"services/io/juggler/condition":{"description":"input.output juggler conditions configuration","read":{"api":{"/io/juggler/conditions/config/*":["*"],"/io/*":["*"]}},"write":{"api":["/io/juggler/conditions/config/*"]},"source":["/io/juggler/conditions/*"]}}
